{"route":[{"routeID":11325,"agencyID":88,"shortName":"Charter","longName":"Charter Service","routeType":3,"sequence":0,"description":"","color":"FFEE05","textColor":"000000","onDemand":0,"calcETA":0,"created":"0000-00-00 00:00:00","updated":"2019-01-26 19:54:36","hidden":1,"disabled":0,"deleted":null,"scheduleURL":"","scheduleURLType":"","shapeID":0,"schedAdh":0,"aliases":"","source":null,"LastETACalc":0,"routeCode":"","special_service":0},{"routeID":11278,"agencyID":88,"shortName":"CC","longName":"121  Campus Connector","routeType":3,"sequence":1,"description":"","color":"EE2135","textColor":"FFFFFF","onDemand":0,"calcETA":1,"created":"0000-00-00 00:00:00","updated":"2019-02-18 21:19:21","hidden":0,"disabled":0,"deleted":null,"scheduleURL":"http:\/\/r.peaktransit.com\/res\/88\/UMN%20Schedule%20Images%20(v4)%20Campus%20Connector.png.png","scheduleURLType":"","shapeID":7601,"schedAdh":0,"aliases":"","source":null,"LastETACalc":1550524761,"routeCode":"","special_service":0},{"routeID":11279,"agencyID":88,"shortName":"UC","longName":"122  University Avenue Circulator","routeType":3,"sequence":2,"description":"","color":"7F53F9","textColor":"FFFFFF","onDemand":0,"calcETA":1,"created":"0000-00-00 00:00:00","updated":"2019-02-18 21:19:21","hidden":0,"disabled":0,"deleted":null,"scheduleURL":"http:\/\/r.peaktransit.com\/res\/88\/UMN%20Schedule%20Images%20(v4)%20University%20Avenue%20Circulator.png.png","scheduleURLType":"","shapeID":7603,"schedAdh":0,"aliases":"","source":null,"LastETACalc":1550524761,"routeCode":"","special_service":0},{"routeID":11280,"agencyID":88,"shortName":"4TH","longName":"123  4th Street Circulator","routeType":3,"sequence":3,"description":"","color":"00B6D2","textColor":"FFFFFF","onDemand":0,"calcETA":1,"created":"0000-00-00 00:00:00","updated":"2019-02-18 21:19:21","hidden":0,"disabled":0,"deleted":null,"scheduleURL":"http:\/\/r.peaktransit.com\/res\/88\/UMN%20Schedule%20Images%204th%20Street%20Circulator%20(v4).png","scheduleURLType":"","shapeID":7605,"schedAdh":0,"aliases":"","source":null,"LastETACalc":1550524761,"routeCode":"","special_service":0},{"routeID":11281,"agencyID":88,"shortName":"SPC","longName":"124  St. Paul Campus Circulator","routeType":3,"sequence":4,"description":"","color":"02C16F","textColor":"FFFFFF","onDemand":0,"calcETA":1,"created":"0000-00-00 00:00:00","updated":"2019-02-18 21:19:23","hidden":0,"disabled":0,"deleted":null,"scheduleURL":"http:\/\/r.peaktransit.com\/res\/88\/St_Paul_Circulator_(v4).png.png","scheduleURLType":"","shapeID":7606,"schedAdh":0,"aliases":"","source":null,"LastETACalc":1550524763,"routeCode":"","special_service":0},{"routeID":11324,"agencyID":88,"shortName":"EBC","longName":"120  East Bank Circulator","routeType":3,"sequence":6,"description":"","color":"FFB69C","textColor":"000000","onDemand":0,"calcETA":1,"created":"0000-00-00 00:00:00","updated":"2019-02-18 21:19:21","hidden":0,"disabled":0,"deleted":null,"scheduleURL":"http:\/\/r.peaktransit.com\/res\/88\/UMN%20Schedule%20Images%20East%20Bank%20Circulator%20(v4).png","scheduleURLType":"","shapeID":7725,"schedAdh":0,"aliases":"","source":null,"LastETACalc":1550524761,"routeCode":"http:\/\/pt-prod-res.s3.amazonaws.com\/res\/88\/East_Ba","special_service":0}],"success":true}